hubtty/__init__.py
hubtty/alembic.ini
hubtty/app.py
hubtty/auth.py
hubtty/commentlink.py
hubtty/config.py
hubtty/db.py
hubtty/dbsupport.py
hubtty/gitrepo.py
hubtty/keymap.py
hubtty/markdown.py
hubtty/mywid.py
hubtty/palette.py
hubtty/requestsexceptions.py
hubtty/sync.py
hubtty/version.py
hubtty/alembic/README
hubtty/alembic/env.py
hubtty/alembic/script.py.mako
hubtty/alembic/versions/1e41885ea284_add_draft_to_pull_request.py
hubtty/alembic/versions/a2af1e2e44ee_.py
hubtty/search/__init__.py
hubtty/search/parser.py
hubtty/search/tokenizer.py
hubtty/view/__init__.py
hubtty/view/diff.py
hubtty/view/mouse_scroll_decorator.py
hubtty/view/pull_request.py
hubtty/view/pull_request_list.py
hubtty/view/repository_list.py
hubtty/view/side_diff.py
hubtty/view/unified_diff.py
hubtty-0.3.5.data/data/share/hubtty/examples/minimal-hubtty.yaml
hubtty-0.3.5.data/data/share/hubtty/examples/openshift-hubtty.yaml
hubtty-0.3.5.data/data/share/hubtty/examples/reference-hubtty.yaml
hubtty-0.3.5.dist-info/AUTHORS
hubtty-0.3.5.dist-info/LICENSE
hubtty-0.3.5.dist-info/METADATA
hubtty-0.3.5.dist-info/WHEEL
hubtty-0.3.5.dist-info/entry_points.txt
hubtty-0.3.5.dist-info/pbr.json
hubtty-0.3.5.dist-info/top_level.txt
hubtty-0.3.5.dist-info/RECORD
