Metadata-Version: 2.1
Name: hubtty
Version: 0.3.5
Summary: Hubtty is a console-based interface to the Github Code Review system.
Home-page: https://hubtty.github.io
Author: The hubtty developers
Author-email: hubtty@mandre.org
Keywords: github console urwid review
Classifier: Topic :: Utilities
Classifier: Intended Audience :: Developers
Classifier: Intended Audience :: Information Technology
Classifier: Intended Audience :: System Administrators
Classifier: License :: OSI Approved :: Apache Software License
Classifier: Operating System :: POSIX :: Linux
Classifier: Programming Language :: Python
Classifier: Programming Language :: Python :: 2
Classifier: Programming Language :: Python :: 2.7
Classifier: Programming Language :: Python :: 3
Classifier: Programming Language :: Python :: 3.5
Classifier: Programming Language :: Python :: 3.6
Classifier: Programming Language :: Python :: 3.7
Classifier: Programming Language :: Python :: 3.8
Classifier: Programming Language :: Python :: 3.9
License-File: LICENSE
License-File: AUTHORS
Requires-Dist: pbr >=0.11
Requires-Dist: urwid >=2.2.0
Requires-Dist: SQLAlchemy >=1.4.0
Requires-Dist: GitPython >=0.3.7
Requires-Dist: python-dateutil
Requires-Dist: requests <3.0.0,>=2.5.3
Requires-Dist: ordereddict
Requires-Dist: alembic >=0.6.4
Requires-Dist: PyYAML >=3.1.0
Requires-Dist: voluptuous >=0.7
Requires-Dist: ply >=3.4
Requires-Dist: six
Requires-Dist: pyxdg
Requires-Dist: mistune <3.0.0,>=2.0
